{
    "topic": "demonstrates the concept of collision and bouncing motion in a 2D space",
    "code": [
        "from _2019.clacks.question import BlocksAndWallExampleMass1e2\n",
        "from _2019.clacks.solution1 import CircleDiagramFromSlidingBlocks1e2\n",
        "\n",
        "\n",
        "class Clacks1(BlocksAndWallExampleMass1e2):\n",
        "    CONFIG = {\n",
        "        \"counter_label\": \"Number of collisions: \",\n",
        "        \"sliding_blocks_config\": {\n",
        "            \"block1_config\": {\n",
        "                \"mass\": 1e0,\n",
        "                \"velocity\": -2.0,\n",
        "                \"sheen_factor\": 0.0,\n",
        "                \"stroke_width\": 1,\n",
        "                \"fill_color\": \"#cccccc\",\n",
        "            },\n",
        "            \"block2_config\": {\n",
        "                \"fill_color\": \"#cccccc\",\n",
        "                \"sheen_factor\": 0.0,\n",
        "                \"stroke_width\": 1,\n",
        "            },\n",
        "        },\n",
        "        \"wait_time\": 15,\n",
        "    }\n",
        "\n",
        "\n",
        "class Clacks100(Clacks1):\n",
        "    CONFIG = {\n",
        "        \"sliding_blocks_config\": {\n",
        "            \"block1_config\": {\n",
        "                \"mass\": 1e2,\n",
        "                \"fill_color\": \"#ff6d58\",\n",
        "                \"velocity\": -0.5,\n",
        "                \"distance\": 5,\n",
        "            },\n",
        "        },\n",
        "        \"wait_time\": 33,\n",
        "    }\n",
        "\n",
        "\n",
        "class Clacks1e4(Clacks1):\n",
        "    CONFIG = {\n",
        "        \"sliding_blocks_config\": {\n",
        "            \"block1_config\": {\n",
        "                \"mass\": 1e4,\n",
        "                \"fill_color\": \"#44c5ae\",\n",
        "                \"distance\": 5,\n",
        "                \"velocity\": -0.7,\n",
        "            },\n",
        "        },\n",
        "        \"wait_time\": 32,\n",
        "    }\n",
        "\n",
        "\n",
        "class Clacks1e6(Clacks1):\n",
        "    CONFIG = {\n",
        "        \"sliding_blocks_config\": {\n",
        "            \"block1_config\": {\n",
        "                \"mass\": 1e6,\n",
        "                \"fill_color\": \"#2fb9de\",\n",
        "                \"velocity\": -0.5,\n",
        "                \"distance\": 5,\n",
        "            },\n",
        "        },\n",
        "        \"wait_time\": 26,\n",
        "    }\n",
        "\n",
        "\n",
        "class SlowClacks100(Clacks1):\n",
        "    CONFIG = {\n",
        "        \"sliding_blocks_config\": {\n",
        "            \"block1_config\": {\n",
        "                \"mass\": 1e2,\n",
        "                \"fill_color\": \"#ff6666\",\n",
        "                \"velocity\": -0.25,\n",
        "                \"distance\": 4.5,\n",
        "            },\n",
        "        },\n",
        "        \"wait_time\": 65,\n",
        "    }\n",
        "\n",
        "\n",
        "class Clacks100VectorEvolution(CircleDiagramFromSlidingBlocks1e2):\n",
        "    CONFIG = {\n",
        "        \"BlocksAndWallSceneClass\": SlowClacks100,\n",
        "        \"show_dot\": False,\n",
        "        \"show_vector\": True,\n",
        "    }\n"
    ]
}